Java12BianchengXuexiShouceChuyi/README.md
Java12BianchengXuexiShouceChuyi/__init__.py
Java12BianchengXuexiShouceChuyi/__main__.py
Java12BianchengXuexiShouceChuyi/file.epub
Java12BianchengXuexiShouceChuyi/index.html
Java12BianchengXuexiShouceChuyi/css/__init__.py
Java12BianchengXuexiShouceChuyi/css/annotations.css
Java12BianchengXuexiShouceChuyi/css/main.css
Java12BianchengXuexiShouceChuyi/css/normalize.css
Java12BianchengXuexiShouceChuyi/css/popup.css
Java12BianchengXuexiShouceChuyi/font/__init__.py
Java12BianchengXuexiShouceChuyi/font/fontello.eot
Java12BianchengXuexiShouceChuyi/font/fontello.svg
Java12BianchengXuexiShouceChuyi/font/fontello.ttf
Java12BianchengXuexiShouceChuyi/font/fontello.woff
Java12BianchengXuexiShouceChuyi/img/__init__.py
Java12BianchengXuexiShouceChuyi/img/annotator-glyph-sprite.png
Java12BianchengXuexiShouceChuyi/img/annotator-icon-sprite.png
Java12BianchengXuexiShouceChuyi/img/apple-touch-icon.png
Java12BianchengXuexiShouceChuyi/img/cancelfullscreen.png
Java12BianchengXuexiShouceChuyi/img/close.png
Java12BianchengXuexiShouceChuyi/img/fullscreen.png
Java12BianchengXuexiShouceChuyi/img/loader.gif
Java12BianchengXuexiShouceChuyi/img/menu-icon.png
Java12BianchengXuexiShouceChuyi/img/save.png
Java12BianchengXuexiShouceChuyi/img/saved.png
Java12BianchengXuexiShouceChuyi/img/settings-s.png
Java12BianchengXuexiShouceChuyi/img/settings.png
Java12BianchengXuexiShouceChuyi/img/star.png
Java12BianchengXuexiShouceChuyi/js/__init__.py
Java12BianchengXuexiShouceChuyi/js/epub.js
Java12BianchengXuexiShouceChuyi/js/epub.min.js
Java12BianchengXuexiShouceChuyi/js/epub.min.map
Java12BianchengXuexiShouceChuyi/js/hooks.min.js
Java12BianchengXuexiShouceChuyi/js/hooks.min.map
Java12BianchengXuexiShouceChuyi/js/reader.js
Java12BianchengXuexiShouceChuyi/js/reader.js.map
Java12BianchengXuexiShouceChuyi/js/reader.min.js
Java12BianchengXuexiShouceChuyi/js/reader.min.map
Java12BianchengXuexiShouceChuyi/js/hooks/__init__.py
java_12_biancheng_xuexi_shouce_chuyi-2024.3.5.0.dist-info/METADATA
java_12_biancheng_xuexi_shouce_chuyi-2024.3.5.0.dist-info/WHEEL
java_12_biancheng_xuexi_shouce_chuyi-2024.3.5.0.dist-info/entry_points.txt
java_12_biancheng_xuexi_shouce_chuyi-2024.3.5.0.dist-info/top_level.txt
java_12_biancheng_xuexi_shouce_chuyi-2024.3.5.0.dist-info/RECORD
